pyorbbec-2.4.3.dist-info/licenses/LICENSE
pyorbbecsdk/__init__.py
pyorbbecsdk/__version__.py
pyorbbec-2.4.3.dist-info/METADATA
pyorbbec-2.4.3.dist-info/WHEEL
pyorbbec-2.4.3.dist-info/top_level.txt
pyorbbec-2.4.3.dist-info/RECORD
