Metadata-Version: 2.4
Name: pyorbbec
Version: 2.4.3
Summary: Your package description
Home-page: https://orbbec.com.cn/
Author: alvisli
Author-email: 605633002@qq.com
Classifier: Programming Language :: Python :: 3
Classifier: License :: OSI Approved :: MIT License
Requires-Python: >=3.8
License-File: LICENSE
Requires-Dist: requests
Dynamic: author
Dynamic: author-email
Dynamic: classifier
Dynamic: home-page
Dynamic: license-file
Dynamic: requires-dist
Dynamic: requires-python
Dynamic: summary
